{"changed": 3345, "changed_30": 381, "changed_365": 1242, "changed_7": 48, "changers": 19, "changers_30": 12, "changers_365": 17, "changers_7": 9, "closed": 1167, "closed_30": 39, "closed_365": 242, "closed_7": 22, "closers": 18, "closers_30": 9, "closers_365": 13, "closers_7": 5, "diff_netchanged_30": 292, "diff_netchanged_365": -829, "diff_netchanged_7": -251, "diff_netchangers_30": 1, "diff_netchangers_365": -1, "diff_netchangers_7": 1, "diff_netclosed_30": 17, "diff_netclosed_365": -597, "diff_netclosed_7": 20, "diff_netclosers_30": 2, "diff_netclosers_365": -3, "diff_netclosers_7": 3, "diff_netopened_30": -8, "diff_netopened_365": -309, "diff_netopened_7": 11, "diff_netopeners_30": 2, "diff_netopeners_365": -2, "diff_netopeners_7": 0, "first_date": "2012-09-02", "last_date": "2014-12-08", "opened": 1438, "opened_30": 39, "opened_365": 451, "opened_7": 16, "openers": 20, "openers_30": 10, "openers_365": 16, "openers_7": 3, "percentage_changed_30": 328, "percentage_changed_365": 40, "percentage_changed_7": 83, "percentage_changers_30": 9, "percentage_changers_365": 5, "percentage_changers_7": 12, "percentage_closed_30": 77, "percentage_closed_365": 71, "percentage_closed_7": 1000, "percentage_closers_30": 28, "percentage_closers_365": 18, "percentage_closers_7": 150, "percentage_opened_30": 17, "percentage_opened_365": 40, "percentage_opened_7": 220, "percentage_openers_30": 25, "percentage_openers_365": 11, "percentage_openers_7": 0, "trackers": 1}