{"diff_netsenders_30": 0, "diff_netsenders_365": -25, "diff_netsenders_7": 1, "diff_netsent_30": 1081, "diff_netsent_365": -8724, "diff_netsent_7": 186, "first_date": "2012-04-19", "last_date": "2016-04-21", "percentage_senders_30": 0, "percentage_senders_365": 35, "percentage_senders_7": 8, "percentage_sent_30": 164, "percentage_sent_365": 28, "percentage_sent_7": 37, "repositories": 7, "senders": 121, "senders_30": 20, "senders_365": 46, "senders_7": 13, "senders_init": 115, "senders_response": 98, "sent": 81370, "sent_30": 1738, "sent_365": 21403, "sent_7": 684, "sent_response": 47232, "threads": 34138}