{"diff_netsenders_30": 0, "diff_netsenders_365": 0, "diff_netsenders_7": 0, "diff_netsent_30": 3, "diff_netsent_365": -673, "diff_netsent_7": 1, "first_date": "2011-01-09", "last_date": "2014-12-25", "percentage_senders_30": 0, "percentage_senders_365": 0, "percentage_senders_7": 0, "percentage_sent_30": 60, "percentage_sent_365": 60, "percentage_sent_7": 100, "repositories": 2, "senders": 4, "senders_30": 1, "senders_365": 3, "senders_7": 1, "senders_init": 3, "senders_response": 4, "sent": 1844, "sent_30": 8, "sent_365": 436, "sent_7": 2, "sent_response": 1663, "threads": 181}