{"diff_netsenders_30": 3, "diff_netsenders_365": -17, "diff_netsenders_7": 13, "diff_netsent_30": -242, "diff_netsent_365": -16249, "diff_netsent_7": 117, "first_date": "2011-01-09", "last_date": "2014-10-21", "percentage_senders_30": 6, "percentage_senders_365": 14, "percentage_senders_7": 50, "percentage_sent_30": 25, "percentage_sent_365": 57, "percentage_sent_7": 91, "repositories": 7, "senders": 153, "senders_30": 51, "senders_365": 101, "senders_7": 39, "senders_init": 132, "senders_response": 146, "sent": 47434, "sent_30": 713, "sent_365": 11989, "sent_7": 245, "sent_response": 32596, "threads": 14838}