{"diff_netsenders_30": -5, "diff_netsenders_365": -15, "diff_netsenders_7": -3, "diff_netsent_30": 422, "diff_netsent_365": -19593, "diff_netsent_7": -106, "first_date": "2011-01-09", "last_date": "2014-12-03", "percentage_senders_30": 9, "percentage_senders_365": 12, "percentage_senders_7": 12, "percentage_sent_30": 52, "percentage_sent_365": 59, "percentage_sent_7": 30, "repositories": 7, "senders": 155, "senders_30": 47, "senders_365": 101, "senders_7": 22, "senders_init": 134, "senders_response": 146, "sent": 55409, "sent_30": 1222, "sent_365": 13259, "sent_7": 237, "sent_response": 37006, "threads": 18403}