{"diff_netsenders_30": 7, "diff_netsenders_365": -39, "diff_netsenders_7": 0, "diff_netsent_30": -13, "diff_netsent_365": -6527, "diff_netsent_7": -19, "first_date": "2012-04-19", "last_date": "2016-03-15", "percentage_senders_30": 58, "percentage_senders_365": 41, "percentage_senders_7": 0, "percentage_sent_30": 11, "percentage_sent_365": 63, "percentage_sent_7": 46, "repositories": 7, "senders": 168, "senders_30": 19, "senders_365": 56, "senders_7": 12, "senders_init": 145, "senders_response": 157, "sent": 52330, "sent_30": 98, "sent_365": 3769, "sent_7": 22, "sent_response": 37366, "threads": 14964}