{"authors.": {"authors": ["Jessica Wang", "Alena Prokharchyk", "Brian Federle", "Anthony Xu", "Kelven Yang", "Prasanna Santhanam", "Sheng Yang", "Alex Huang", "Rohit Yadav", "Min Chen"], "commits": [4733, 3149, 2299, 1569, 1296, 1177, 1158, 1087, 1081, 1072], "id": [13, 27, 81, 17, 15, 59, 64, 24, 143, 190]}, "authors.last month": {"authors": ["Jessica Wang", "Girish Shilamkar", "Rohit Yadav", "Mike Tutkowski", "Sanjay Tripathi", "Daan Hoogland", "Edison Su", "Min Chen", "Chandan Purushothama", "Nitin Mehta"], "commits": [66, 37, 32, 25, 23, 22, 21, 21, 16, 16], "id": [13, 261, 143, 8, 102, 286, 14, 190, 325, 75]}, "authors.last year": {"authors": ["Girish Shilamkar", "Min Chen", "Jessica Wang", "Rohit Yadav", "Daan Hoogland", "Hugo Trippaers", "Alena Prokharchyk", "Brian Federle", "Edison Su", "Santhosh Edukulla"], "commits": [404, 375, 361, 358, 289, 239, 222, 218, 198, 179], "id": [261, 190, 13, 143, 286, 133, 27, 81, 14, 327]}}