{"actions": 271778, "added_lines": 16884205.0, "added_lines_30": 11395.0, "added_lines_365": 401742.0, "added_lines_7": 866.0, "authors": 338, "authors_30": 28, "authors_365": 109, "authors_7": 2, "avg_commits_author": 126.68, "avg_commits_month": 667.06, "avg_files_author": 263.88, "avg_files_month": 1389.48, "branches": 245, "commits": 42692, "commits_30": 140, "commits_365": 3096, "commits_7": 9, "committers": 338, "diff_netadded_lines_30": -10388.0, "diff_netadded_lines_365": -660445.0, "diff_netadded_lines_7": 281.0, "diff_netauthors_30": -3, "diff_netauthors_365": -32, "diff_netauthors_7": -6, "diff_netcommits_30": -20, "diff_netcommits_365": -4252, "diff_netcommits_7": -14, "diff_netfiles_30": -377, "diff_netfiles_365": -4466, "diff_netfiles_7": -23, "diff_netnewauthors_30": -7, "diff_netnewauthors_365": -20, "diff_netnewauthors_7": 0, "diff_netremoved_lines_30": -1684.0, "diff_netremoved_lines_365": 539821.0, "diff_netremoved_lines_7": -2633.0, "files": 88927, "files_30": 1018, "files_365": 10857, "files_7": 263, "first_date": "2010-08-11", "last_date": "2015-12-24", "newauthors": 338, "newauthors_30": 1, "newauthors_365": 50, "newauthors_7": 0, "percentage_added_lines_30": 47, "percentage_added_lines_365": 62, "percentage_added_lines_7": 48, "percentage_authors_30": 9, "percentage_authors_365": 22, "percentage_authors_7": 75, "percentage_commits_30": 12, "percentage_commits_365": 57, "percentage_commits_7": 60, "percentage_files_30": 27, "percentage_files_365": 29, "percentage_files_7": 8, "percentage_newauthors_30": 87, "percentage_newauthors_365": 28, "percentage_newauthors_7": 0, "percentage_removed_lines_30": 14, "percentage_removed_lines_365": 30, "percentage_removed_lines_7": 83, "removed_lines": 14700138.0, "removed_lines_30": 10143.0, "removed_lines_365": 2282520.0, "removed_lines_7": 529.0, "repositories": 1}