{"actions": 147882, "added_lines": 10304619.0, "added_lines_30": 580.0, "added_lines_365": 52391.0, "added_lines_7": 8.0, "authors": 32, "authors_30": 1, "authors_365": 13, "authors_7": 1, "avg_commits_author": 786.38, "avg_commits_month": 441.47, "avg_files_author": 1263.75, "avg_files_month": 709.47, "branches": 81, "commits": 25164, "commits_30": 27, "commits_365": 809, "commits_7": 6, "committers": 32, "diff_netadded_lines_30": 566.0, "diff_netadded_lines_365": -1544609.0, "diff_netadded_lines_7": -26.0, "diff_netauthors_30": 0, "diff_netauthors_365": -4, "diff_netauthors_7": 0, "diff_netcommits_30": 25, "diff_netcommits_365": -3524, "diff_netcommits_7": 0, "diff_netfiles_30": 23, "diff_netfiles_365": -10905, "diff_netfiles_7": 2, "diff_netnewauthors_30": 0, "diff_netnewauthors_365": 0, "diff_netnewauthors_7": 0, "diff_netremoved_lines_30": 142.0, "diff_netremoved_lines_365": -1613183.0, "diff_netremoved_lines_7": -2.0, "files": 40440, "files_30": 31, "files_365": 938, "files_7": 6, "first_date": "2010-08-11", "last_date": "2015-05-22", "newauthors": 32, "newauthors_30": 0, "newauthors_365": 0, "newauthors_7": 0, "percentage_added_lines_30": 4042, "percentage_added_lines_365": 96, "percentage_added_lines_7": 76, "percentage_authors_30": 0, "percentage_authors_365": 23, "percentage_authors_7": 0, "percentage_commits_30": 1250, "percentage_commits_365": 81, "percentage_commits_7": 0, "percentage_files_30": 287, "percentage_files_365": 92, "percentage_files_7": 50, "percentage_newauthors_30": 0, "percentage_newauthors_365": 0, "percentage_newauthors_7": 0, "percentage_removed_lines_30": 1775, "percentage_removed_lines_365": 98, "percentage_removed_lines_7": 25, "removed_lines": 6986580.0, "removed_lines_30": 150.0, "removed_lines_365": 25110.0, "removed_lines_7": 6.0, "repositories": 2}