{"diff_netsenders_30": -1, "diff_netsenders_365": 1, "diff_netsenders_7": 0, "diff_netsent_30": -65, "diff_netsent_365": 389, "diff_netsent_7": 0, "first_date": "2011-01-09", "last_date": "2015-01-01", "percentage_senders_30": 33, "percentage_senders_365": 20, "percentage_senders_7": 0, "percentage_sent_30": 57, "percentage_sent_365": 113, "percentage_sent_7": 0, "repositories": 4, "senders": 6, "senders_30": 2, "senders_365": 6, "senders_7": 1, "senders_init": 5, "senders_response": 6, "sent": 1075, "sent_30": 48, "sent_365": 732, "sent_7": 4, "sent_response": 786, "threads": 289}