{"actions": 250865, "added_lines": 16387442.0, "added_lines_30": 26842, "added_lines_365": 1276814, "added_lines_7": 4441, "authors": 291, "authors_30": 31, "authors_365": 148, "authors_7": 15, "avg_commits_author": 133.8007, "avg_commits_month": 734.6415, "avg_files_author": 279.3677, "avg_files_month": 1533.8868, "branches": 185, "commits": 38936, "commits_30": 247, "commits_365": 6269, "commits_7": 60, "committers": 155, "diff_netadded_lines_30": -18291, "diff_netadded_lines_365": -4760101, "diff_netadded_lines_7": -2516, "diff_netauthors_30": -40, "diff_netauthors_365": -4, "diff_netauthors_7": 2, "diff_netcommits_30": -379, "diff_netcommits_365": -5248, "diff_netcommits_7": 6, "diff_netfiles_30": -2558, "diff_netfiles_365": -24214, "diff_netfiles_7": 239, "diff_netremoved_lines_30": -1060116, "diff_netremoved_lines_365": -1900992, "diff_netremoved_lines_7": -1709, "files": 81296, "files_30": 823, "files_365": 14311, "files_7": 453, "first_date": "2010-08-11", "last_date": "2015-01-14", "percentage_added_lines_30": 40, "percentage_added_lines_365": 78, "percentage_added_lines_7": 36, "percentage_authors_30": 56, "percentage_authors_365": 2, "percentage_authors_7": 15, "percentage_commits_30": 60, "percentage_commits_365": 45, "percentage_commits_7": 11, "percentage_files_30": 75, "percentage_files_365": 62, "percentage_files_7": 111, "percentage_removed_lines_30": 98, "percentage_removed_lines_365": 51, "percentage_removed_lines_7": 42, "removed_lines": 12355953.0, "removed_lines_30": 16800, "removed_lines_365": 1816031, "removed_lines_7": 2271, "repositories": 1}