{"actions": 114800, "added_lines": 6696211.0, "added_lines_30": 41233, "added_lines_365": 3055898, "added_lines_7": 8087, "authors": 76, "authors_30": 16, "authors_365": 50, "authors_7": 8, "avg_commits_author": 157.5526, "avg_commits_month": 244.3673, "avg_files_author": 594.8816, "avg_files_month": 922.6735, "branches": 95, "commits": 11974, "commits_30": 84, "commits_365": 2638, "commits_7": 18, "committers": 38, "diff_netadded_lines_30": -55332, "diff_netadded_lines_365": -1899673, "diff_netadded_lines_7": -45, "diff_netauthors_30": -3, "diff_netauthors_365": 2, "diff_netauthors_7": -1, "diff_netcommits_30": -91, "diff_netcommits_365": -1135, "diff_netcommits_7": -11, "diff_netfiles_30": -308, "diff_netfiles_365": -3453, "diff_netfiles_7": -202, "diff_netremoved_lines_30": -33079, "diff_netremoved_lines_365": -43782, "diff_netremoved_lines_7": -3084, "files": 45211, "files_30": 354, "files_365": 14140, "files_7": 39, "first_date": "2010-08-11", "last_date": "2014-09-12", "percentage_added_lines_30": 57, "percentage_added_lines_365": 38, "percentage_added_lines_7": 0, "percentage_authors_30": 15, "percentage_authors_365": 4, "percentage_authors_7": 11, "percentage_commits_30": 52, "percentage_commits_365": 30, "percentage_commits_7": 37, "percentage_files_30": 46, "percentage_files_365": 19, "percentage_files_7": 83, "percentage_removed_lines_30": 67, "percentage_removed_lines_365": 1, "percentage_removed_lines_7": 71, "removed_lines": 5986094.0, "removed_lines_30": 15776, "removed_lines_365": 2472550, "removed_lines_7": 1241, "repositories": 4}