{"actions": 149623, "added_lines": 7588141.0, "added_lines_30": 914.0, "added_lines_365": 156600.0, "added_lines_7": 393.0, "authors": 104, "authors_30": 6, "authors_365": 48, "authors_7": 2, "avg_commits_author": 190.95, "avg_commits_month": 325.56, "avg_files_author": 515.96, "avg_files_month": 879.67, "branches": 156, "commits": 19859, "commits_30": 26, "commits_365": 1572, "commits_7": 3, "committers": 55, "diff_netadded_lines_30": -15278.0, "diff_netadded_lines_365": -1994932.0, "diff_netadded_lines_7": 389.0, "diff_netauthors_30": -4, "diff_netauthors_365": -9, "diff_netauthors_7": 0, "diff_netcommits_30": -49, "diff_netcommits_365": -2512, "diff_netcommits_7": 1, "diff_netfiles_30": 867, "diff_netfiles_365": -9973, "diff_netfiles_7": 1325, "diff_netnewauthors_30": 0, "diff_netnewauthors_365": -6, "diff_netnewauthors_7": -1, "diff_netremoved_lines_30": 79875.0, "diff_netremoved_lines_365": -1763992.0, "diff_netremoved_lines_7": 93485.0, "files": 53660, "files_30": 1362, "files_365": 5846, "files_7": 1329, "first_date": "2010-08-11", "last_date": "2015-10-01", "newauthors": 104, "newauthors_30": 2, "newauthors_365": 20, "newauthors_7": 0, "percentage_added_lines_30": 94, "percentage_added_lines_365": 92, "percentage_added_lines_7": 9725, "percentage_authors_30": 40, "percentage_authors_365": 15, "percentage_authors_7": 0, "percentage_commits_30": 65, "percentage_commits_365": 61, "percentage_commits_7": 50, "percentage_files_30": 175, "percentage_files_365": 63, "percentage_files_7": 33125, "percentage_newauthors_30": 0, "percentage_newauthors_365": 23, "percentage_newauthors_7": 100, "percentage_removed_lines_30": 577, "percentage_removed_lines_365": 90, "percentage_removed_lines_7": 2337125, "removed_lines": 6638186.0, "removed_lines_30": 93702.0, "removed_lines_365": 191097.0, "removed_lines_7": 93489.0, "repositories": 4}