{"actions": 122739, "added_lines": 6961721.0, "added_lines_30": 46947, "added_lines_365": 1176343, "added_lines_7": 35931, "authors": 81, "authors_30": 16, "authors_365": 46, "authors_7": 12, "avg_commits_author": 178.7037, "avg_commits_month": 273.1132, "avg_files_author": 591.5926, "avg_files_month": 904.1321, "branches": 137, "commits": 14475, "commits_30": 272, "commits_365": 2209, "commits_7": 196, "committers": 40, "diff_netadded_lines_30": 20852, "diff_netadded_lines_365": -4849258, "diff_netadded_lines_7": 34964, "diff_netauthors_30": 2, "diff_netauthors_365": -9, "diff_netauthors_7": 7, "diff_netcommits_30": 180, "diff_netcommits_365": -2484, "diff_netcommits_7": 173, "diff_netfiles_30": 640, "diff_netfiles_365": -12947, "diff_netfiles_7": 326, "diff_netremoved_lines_30": 14215, "diff_netremoved_lines_365": -1879730, "diff_netremoved_lines_7": 24720, "files": 47919, "files_30": 789, "files_365": 8367, "files_7": 350, "first_date": "2010-08-11", "last_date": "2015-02-05", "percentage_added_lines_30": 79, "percentage_added_lines_365": 80, "percentage_added_lines_7": 3615, "percentage_authors_30": 14, "percentage_authors_365": 16, "percentage_authors_7": 140, "percentage_commits_30": 195, "percentage_commits_365": 52, "percentage_commits_7": 752, "percentage_files_30": 429, "percentage_files_365": 60, "percentage_files_7": 1358, "percentage_removed_lines_30": 89, "percentage_removed_lines_365": 51, "percentage_removed_lines_7": 6338, "removed_lines": 6106211.0, "removed_lines_30": 30021, "removed_lines_365": 1756557, "removed_lines_7": 25110, "repositories": 4}