{"actions": 116095, "added_lines": 6738403.0, "added_lines_30": 95752, "added_lines_365": 2847354, "added_lines_7": 43771, "authors": 78, "authors_30": 10, "authors_365": 50, "authors_7": 9, "avg_commits_author": 155.859, "avg_commits_month": 243.14, "avg_files_author": 587.859, "avg_files_month": 917.06, "branches": 108, "commits": 12157, "commits_30": 144, "commits_365": 2561, "commits_7": 57, "committers": 38, "diff_netadded_lines_30": 39405, "diff_netadded_lines_365": -2348702, "diff_netadded_lines_7": 38797, "diff_netauthors_30": -4, "diff_netauthors_365": -2, "diff_netauthors_7": 3, "diff_netcommits_30": 46, "diff_netcommits_365": -1050, "diff_netcommits_7": 39, "diff_netfiles_30": 220, "diff_netfiles_365": -4597, "diff_netfiles_7": 107, "diff_netremoved_lines_30": 46643, "diff_netremoved_lines_365": -503433, "diff_netremoved_lines_7": 29396, "files": 45853, "files_30": 676, "files_365": 13727, "files_7": 250, "first_date": "2010-08-11", "last_date": "2014-10-18", "percentage_added_lines_30": 69, "percentage_added_lines_365": 45, "percentage_added_lines_7": 779, "percentage_authors_30": 28, "percentage_authors_365": 3, "percentage_authors_7": 50, "percentage_commits_30": 46, "percentage_commits_365": 29, "percentage_commits_7": 216, "percentage_files_30": 48, "percentage_files_365": 25, "percentage_files_7": 74, "percentage_removed_lines_30": 207, "percentage_removed_lines_365": 18, "percentage_removed_lines_7": 1083, "removed_lines": 6014198.0, "removed_lines_30": 69087, "removed_lines_365": 2262852, "removed_lines_7": 32108, "repositories": 4}