{"diff_netsenders_30": -3, "diff_netsenders_365": -88, "diff_netsenders_7": 3, "diff_netsent_30": 33, "diff_netsent_365": -9951, "diff_netsent_7": 44, "first_date": "2011-01-09", "last_date": "2014-11-06", "percentage_senders_30": 4, "percentage_senders_365": 21, "percentage_senders_7": 10, "percentage_sent_30": 4, "percentage_sent_365": 42, "percentage_sent_7": 36, "repositories": 6, "senders": 663, "senders_30": 69, "senders_365": 329, "senders_7": 33, "senders_init": 582, "senders_response": 507, "sent": 42173, "sent_30": 711, "sent_365": 13338, "sent_7": 163, "sent_response": 30989, "threads": 11184}