{"diff_netsenders_30": -13, "diff_netsenders_365": -97, "diff_netsenders_7": 11, "diff_netsent_30": -127, "diff_netsent_365": -2025, "diff_netsent_7": 38, "first_date": "2011-01-09", "last_date": "2015-01-30", "percentage_senders_30": 11, "percentage_senders_365": 14, "percentage_senders_7": 35, "percentage_sent_30": 22, "percentage_sent_365": 22, "percentage_sent_7": 44, "repositories": 1, "senders": 1204, "senders_30": 99, "senders_365": 570, "senders_7": 42, "senders_init": 1000, "senders_response": 913, "sent": 20077, "sent_30": 428, "sent_365": 7075, "sent_7": 123, "sent_response": 15384, "threads": 4693}