{"senders.": {"id": [81, 34287, 143, 59, 190, 27, 33996, 33598, 286, 35133], "senders": ["Brian Federle", "jenkins@builds.apache.org", "Rohit Yadav", "Prasanna Santhanam", "Min Chen", "Alena Prokharchyk", "edison@apache.org", "ahuang@apache.org", "Daan Hoogland", "widodh@apache.org"], "sent": [4557, 3083, 2561, 2313, 2278, 2214, 1994, 1971, 1665, 1614]}, "senders.last month": {"id": [286, 143, 34287, 157, 334, 4, 34617, 34600, 116, 2], "senders": ["Daan Hoogland", "Rohit Yadav", "jenkins@builds.apache.org", "Srikanteswararao Talluri", "Rajani Karuturi", "Pierre-Luc Dion", "mtutkowski@apache.org", "mlsorensen@apache.org", "Koushik Das", "David Nalley"], "sent": [246, 157, 45, 45, 17, 16, 15, 11, 9, 5]}, "senders.last year": {"id": [286, 143, 34287, 1, 157, 190, 34189, 334, 34619, 34107], "senders": ["Daan Hoogland", "Rohit Yadav", "jenkins@builds.apache.org", "Sebastien Goasquen", "Srikanteswararao Talluri", "Min Chen", "hugo@apache.org", "Rajani Karuturi", "muralireddy@apache.org", "girish@apache.org"], "sent": [1508, 1436, 603, 564, 536, 421, 363, 354, 290, 266]}}