{"diff_netsenders_30": -2, "diff_netsenders_365": -65, "diff_netsenders_7": -2, "diff_netsent_30": -27, "diff_netsent_365": -1088, "diff_netsent_7": 1, "first_date": "2011-01-09", "last_date": "2015-03-26", "percentage_senders_30": 6, "percentage_senders_365": 26, "percentage_senders_7": 15, "percentage_sent_30": 32, "percentage_sent_365": 47, "percentage_sent_7": 6, "repositories": 1, "senders": 462, "senders_30": 28, "senders_365": 185, "senders_7": 11, "senders_init": 366, "senders_response": 282, "sent": 4396, "sent_30": 55, "sent_365": 1181, "sent_7": 16, "sent_response": 2283, "threads": 2113}