{"diff_netsenders_30": 0, "diff_netsenders_365": -17, "diff_netsenders_7": -3, "diff_netsent_30": -367, "diff_netsent_365": -7662, "diff_netsent_7": 33, "first_date": "2012-05-27", "last_date": "2015-07-04", "percentage_senders_30": 0, "percentage_senders_365": 23, "percentage_senders_7": 33, "percentage_sent_30": 39, "percentage_sent_365": 46, "percentage_sent_7": 35, "repositories": 1, "senders": 90, "senders_30": 19, "senders_365": 56, "senders_7": 6, "senders_init": 89, "senders_response": 73, "sent": 48480, "sent_30": 561, "sent_365": 8956, "sent_7": 125, "sent_response": 18921, "threads": 29559}