{"senders.": {"id": [1193, 1749, 59, 2015, 1090, 1081, 1466, 2574, 2, 124], "senders": ["bfederle@apache.org", "Apache Jenkins Server", "Prasanna Santhanam", "mchen@apache.org", "alena1108@apache.org", "ahuang@apache.org", "edison@apache.org", "widodh@apache.org", "David Nalley", "chip.childers@gmail.com"], "sent": [4437, 2979, 2313, 2205, 2198, 1971, 1913, 1416, 1399, 1361]}, "senders.last month": {"id": [1653, 1367, 2352, 1749, 1574, 2074, 1222, 116, 114, 2107], "senders": ["hugo@apache.org", "dahn@apache.org", "sebgoa@apache.org", "Apache Jenkins Server", "girish@apache.org", "mtutkowski@apache.org", "buildbot@apache.org", "Koushik Das", "Jayapal Uradi", "nitin@apache.org"], "sent": [127, 98, 97, 65, 30, 22, 17, 17, 12, 11]}, "senders.last year": {"id": [1749, 1193, 2015, 1367, 2352, 1653, 1574, 13, 1423, 1466], "senders": ["Apache Jenkins Server", "bfederle@apache.org", "mchen@apache.org", "dahn@apache.org", "sebgoa@apache.org", "hugo@apache.org", "girish@apache.org", "Jessica Wang", "devdeep@apache.org", "edison@apache.org"], "sent": [1257, 1230, 1057, 719, 639, 566, 557, 550, 528, 522]}}