{"diff_netsenders_30": 5, "diff_netsenders_365": 17, "diff_netsenders_7": -2, "diff_netsent_30": 44, "diff_netsent_365": -11604, "diff_netsent_7": 193, "first_date": "2011-01-09", "last_date": "2014-07-31", "percentage_senders_30": 12, "percentage_senders_365": 30, "percentage_senders_7": 6, "percentage_sent_30": 6, "percentage_sent_365": 43, "percentage_sent_7": 139, "repositories": 1, "senders": 85, "senders_30": 44, "senders_365": 72, "senders_7": 27, "senders_init": 85, "senders_response": 65, "sent": 43484, "sent_30": 766, "sent_365": 15088, "sent_7": 331, "sent_response": 17141, "threads": 26343}