{"diff_netsenders_30": -1, "diff_netsenders_365": 38, "diff_netsenders_7": -14, "diff_netsent_30": 49, "diff_netsent_365": -277, "diff_netsent_7": -39, "first_date": "2011-01-09", "last_date": "2014-09-14", "percentage_senders_30": 3, "percentage_senders_365": 44, "percentage_senders_7": 87, "percentage_sent_30": 70, "percentage_sent_365": 16, "percentage_sent_7": 92, "repositories": 1, "senders": 162, "senders_30": 30, "senders_365": 123, "senders_7": 2, "senders_init": 87, "senders_response": 143, "sent": 3163, "sent_30": 119, "sent_365": 1443, "sent_7": 3, "sent_response": 2590, "threads": 573}