{"diff_netsenders_30": 19, "diff_netsenders_365": -161, "diff_netsenders_7": -2, "diff_netsent_30": 98, "diff_netsent_365": -2324, "diff_netsent_7": 11, "first_date": "2012-04-23", "last_date": "2015-07-20", "percentage_senders_30": 25, "percentage_senders_365": 25, "percentage_senders_7": 4, "percentage_sent_30": 33, "percentage_sent_365": 27, "percentage_sent_7": 10, "repositories": 1, "senders": 1306, "senders_30": 95, "senders_365": 480, "senders_7": 43, "senders_init": 1081, "senders_response": 991, "sent": 22544, "sent_30": 394, "sent_365": 5997, "sent_7": 114, "sent_response": 17284, "threads": 5260}