{"senders.": {"id": [288, 1, 32958, 34666, 33242, 2, 34919, 38, 124, 25], "senders": ["Geoff Higginbottom", "Sebastien Goasquen", "aemneina", "nux@li.nux.ro", "indrapr", "David Nalley", "shanker.balan@shapeblue.com", "Nitin", "Chip Childers", "Chiradeep Vittal"], "sent": [502, 453, 424, 405, 301, 290, 279, 272, 246, 237]}, "senders.last month": {"id": [34609, 286, 33242, 33652, 1, 293, 32989, 143, 34199, 34334], "senders": ["motty.cruz@gmail.com", "Daan Hoogland", "indrapr", "angal.sh@gmail.com", "Sebastien Goasquen", "Amogh Vasekar", "kirkk", "Rohit Yadav", "ian@duffrecords.com", "joseegas@farmaenlace.com"], "sent": [41, 35, 32, 25, 25, 18, 17, 15, 14, 14]}, "senders.last year": {"id": [34666, 288, 34817, 34919, 34609, 1, 286, 33340, 33293, 34787], "senders": ["nux@li.nux.ro", "Geoff Higginbottom", "refond.gmrt@gmail.com", "shanker.balan@shapeblue.com", "motty.cruz@gmail.com", "Sebastien Goasquen", "Daan Hoogland", "andrija", "mozg31337", "rafaelweingartner@gmail.com"], "sent": [260, 239, 215, 188, 182, 154, 152, 139, 138, 136]}}