{"actions": 3091, "added_lines": 80700.0, "added_lines_30": 39962, "added_lines_365": 1360801, "added_lines_7": 4817, "authors": 1, "authors_30": 1, "authors_365": 1, "authors_7": 0, "avg_commits_author": 685.0, "avg_commits_month": 23.6207, "avg_files_author": 2261.0, "avg_files_month": 77.9655, "branches": 44, "commits": 685, "commits_30": 19, "commits_365": 247, "commits_7": 0, "committers": 1, "diff_netadded_lines_30": 5372, "diff_netadded_lines_365": -4921080, "diff_netadded_lines_7": -2963, "diff_netauthors_30": 0, "diff_netauthors_365": 0, "diff_netauthors_7": 0, "diff_netcommits_30": 10, "diff_netcommits_365": -61, "diff_netcommits_7": 0, "diff_netfiles_30": -64, "diff_netfiles_365": 441, "diff_netfiles_7": 0, "diff_netremoved_lines_30": 1045907, "diff_netremoved_lines_365": -1984246, "diff_netremoved_lines_7": -4316, "files": 2261, "files_30": 68, "files_365": 1285, "files_7": 0, "first_date": "2010-08-11", "last_date": "2014-12-17", "percentage_added_lines_30": 15, "percentage_added_lines_365": 78, "percentage_added_lines_7": 38, "percentage_authors_30": 0, "percentage_authors_365": 0, "percentage_authors_7": 0, "percentage_commits_30": 111, "percentage_commits_365": 19, "percentage_commits_7": 0, "percentage_files_30": 48, "percentage_files_365": 52, "percentage_files_7": 0, "percentage_removed_lines_30": 3959, "percentage_removed_lines_365": 51, "percentage_removed_lines_7": 62, "removed_lines": 109665.0, "removed_lines_30": 1072320, "removed_lines_365": 1863777, "removed_lines_7": 2565, "repositories": 2}