{"closers.": {"closed": [498, 418, 255, 199, 195, 181, 175, 157, 157, 150], "closers": ["Chip Childers", "Rayees Namathponnan", "Sudha Ponnaganti", "Chandan Purushothama", "Sangeetha Hariharan", "Sailaja Mada", "Shweta Agarwal", "Sanjeev Neelarapu", "Srikanteswararao Talluri", "Abhinav Roy"], "id": [124, 277, 34990, 325, 70, 301, 486, 260, 157, 20219]}, "closers.last month": {"closed": [11, 7, 4, 4, 3, 3, 3, 2, 2, 2], "closers": ["Jessica Wang", "Shweta Agarwal", "prashantkm", "Sailaja Mada", "Rohit Yadav", "Santhosh Edukulla", "Srikanteswararao Talluri", "Chandan Purushothama", "Mike Tutkowski", "Sheng Yang"], "id": [13, 486, 32973, 301, 143, 327, 157, 325, 8, 64]}, "closers.last year": {"closed": [218, 62, 56, 53, 51, 47, 42, 39, 37, 34], "closers": ["Rayees Namathponnan", "Jessica Wang", "Manasa Veloori", "Shweta Agarwal", "Sangeetha Hariharan", "Anshul Gangwar", "Chandan Purushothama", "Gaurav Aradhye", "Rohit Yadav", "Abhinav Roy"], "id": [277, 13, 34518, 486, 70, 244, 325, 276, 143, 20219]}, "openers.": {"id": [277, 325, 70, 301, 260, 157, 486, 32971, 20219, 32984], "opened": [487, 333, 324, 260, 203, 197, 173, 151, 147, 146], "openers": ["Rayees Namathponnan", "Chandan Purushothama", "Sangeetha Hariharan", "Sailaja Mada", "Sanjeev Neelarapu", "Srikanteswararao Talluri", "Shweta Agarwal", "tsp", "Abhinav Roy", "swamy"]}, "openers.last month": {"id": [325, 276, 13, 33183, 102, 326, 190, 33088, 33190, 157], "opened": [24, 12, 10, 9, 9, 8, 7, 7, 6, 5], "openers": ["Chandan Purushothama", "Gaurav Aradhye", "Jessica Wang", "ashutoshk", "Sanjay Tripathi", "Damoder Reddy", "Min Chen", "nitinme", "tqlogan", "Srikanteswararao Talluri"]}, "openers.last year": {"id": [277, 325, 70, 276, 486, 260, 13, 157, 33088, 190], "opened": [195, 147, 101, 88, 79, 78, 67, 65, 60, 53], "openers": ["Rayees Namathponnan", "Chandan Purushothama", "Sangeetha Hariharan", "Gaurav Aradhye", "Shweta Agarwal", "Sanjeev Neelarapu", "Jessica Wang", "Srikanteswararao Talluri", "nitinme", "Min Chen"]}}