{"diff_netsenders_30": [-8, 0, -1, -14, -4, -1, 0], "diff_netsenders_365": [-132, 0, -23, -210, -45, -30, -5], "diff_netsenders_7": [-1, 0, 1, -16, 0, -8, 0], "diff_netsent_30": [-712, -883, -339, -108, -11, -26, 0], "diff_netsent_365": [-71, -2311, -4466, -2823, -902, -598, -6], "diff_netsent_7": [28, 183, 170, -20, 0, -9, 0], "first_date": ["2012-04-19", "2013-05-26", "2012-05-27", "2012-04-23", "2011-01-09", "2013-02-12", "2013-04-24"], "last_date": ["2016-01-21", "2013-10-28", "2016-01-20", "2016-01-21", "2016-01-07", "2016-01-21", "2015-01-09"], "mailing_list_url": ["http://mail-archives.apache.org/mod_mbox/cloudstack-dev", "http://mail-archives.apache.org/mod_mbox/cloudstack-issues", "http://mail-archives.apache.org/mod_mbox/cloudstack-commits", "http://mail-archives.apache.org/mod_mbox/cloudstack-users", "http://mail-archives.apache.org/mod_mbox/cloudstack-users-cn", "http://mail-archives.apache.org/mod_mbox/cloudstack-marketing", "http://mail-archives.apache.org/mod_mbox/cloudstack-announce"], "percentage_senders_30": [13, 0, 9, 17, 19, 6, 0], "percentage_senders_365": [33, 0, 37, 36, 24, 28, 100], "percentage_senders_7": [3, 0, 20, 53, 0, 88, 0], "percentage_sent_30": [33, 47, 57, 36, 40, 55, 0], "percentage_sent_365": [0, 14, 41, 39, 63, 52, 100], "percentage_sent_7": [7, 78, 629, 32, 0, 90, 0], "repositories": [1, 1, 1, 1, 1, 1, 1], "senders": [989, 1, 92, 1380, 528, 204, 8], "senders_30": [52, 1, 9, 65, 16, 14, 0], "senders_365": [266, 1, 39, 367, 139, 77, 0], "senders_7": [27, 1, 6, 14, 0, 1, 0], "senders_init": [779, 0, 91, 1149, 429, 108, 7], "senders_response": [782, 1, 73, 1038, 306, 178, 1], "sent": [77488, 10, 50970, 24207, 4744, 3945, 16], "sent_30": [1424, 978, 255, 192, 16, 21, 0], "sent_365": [18690, 13488, 6410, 4292, 521, 541, 0], "sent_7": [417, 417, 197, 41, 0, 1, 0], "sent_response": [64071, 10, 20657, 18555, 2438, 3195, 2], "threads": [13417, 0, 30313, 5652, 2306, 750, 14]}