{"diff_netsenders_30": -11, "diff_netsenders_365": -271, "diff_netsenders_7": 13, "diff_netsent_30": 874, "diff_netsent_365": -41983, "diff_netsent_7": -188, "domains": 731, "first_date": "2011-01-09", "last_date": "2015-06-01", "organizations": 80, "percentage_senders_30": 6, "percentage_senders_365": 23, "percentage_senders_7": 19, "percentage_sent_30": 28, "percentage_sent_365": 47, "percentage_sent_7": 19, "repositories": 7, "senders": 2197, "senders_30": 172, "senders_365": 872, "senders_7": 79, "senders_init": 1891, "senders_response": 1613, "sent": 139857, "sent_30": 3895, "sent_365": 46414, "sent_7": 771, "sent_response": 91521, "threads": 48336}