{"actions": 232227, "added_lines": 16016550.0, "added_lines_14": 136866.0, "added_lines_180": 2175544.0, "added_lines_30": 172798.0, "added_lines_365": 5720065.0, "added_lines_60": 314797.0, "added_lines_7": 60005.0, "added_lines_730": 11820264.0, "added_lines_90": 490837.0, "authors": 239, "authors_14": 39, "authors_180": 111, "authors_30": 59, "authors_365": 153, "authors_60": 75, "authors_7": 27, "authors_730": 208, "authors_90": 87, "avg_commits_author": 143.5168, "avg_commits_month": 794.3488, "avg_files_author": 326.1597, "avg_files_month": 1805.2558, "branches": 87, "commits": 34157, "commits_14": 281, "commits_180": 4271, "commits_30": 629, "commits_365": 11204, "commits_60": 1125, "commits_7": 96, "commits_730": 20664, "commits_90": 1958, "committers": 137, "companies": 10, "companies_2006": 0, "companies_2009": 0, "companies_2012": 7, "core": 30, "diff_netadded_lines_30": -19564, "diff_netadded_lines_365": -429470, "diff_netadded_lines_7": -67088, "diff_netauthors_30": 2, "diff_netauthors_365": 35, "diff_netauthors_7": -2, "diff_netcommits_30": 131, "diff_netcommits_365": 1912, "diff_netcommits_7": -89, "diff_netfiles_30": -1366, "diff_netfiles_365": 1932, "diff_netfiles_7": -277, "diff_netremoved_lines_30": 5743, "diff_netremoved_lines_365": -280647, "diff_netremoved_lines_7": 97042, "domains": 134, "files": 77626, "files_14": 1208, "files_180": 14614, "files_30": 2430, "files_365": 34512, "files_60": 5600, "files_7": 522, "files_730": 62993, "files_90": 6853, "first_date": "2010-08-11", "last_date": "2014-04-07", "occasional": 177, "percentage_added_lines_30": 13, "percentage_added_lines_365": 7, "percentage_added_lines_7": 87, "percentage_authors_30": 3, "percentage_authors_365": 29, "percentage_authors_7": 6, "percentage_commits_30": 27, "percentage_commits_365": 21, "percentage_commits_7": 47, "percentage_files_30": 36, "percentage_files_365": 5, "percentage_files_7": 36, "percentage_removed_lines_30": 4, "percentage_removed_lines_365": 7, "percentage_removed_lines_7": 1081, "regular": 31, "removed_lines": 11062741.0, "removed_lines_14": 114454.0, "removed_lines_180": 1919736.0, "removed_lines_30": 126100.0, "removed_lines_365": 3558415.0, "removed_lines_60": 246409.0, "removed_lines_7": 106023.0, "removed_lines_730": 7397883.0, "removed_lines_90": 359809.0, "repositories": 4, "type": "git", "url": "https://git-wip-us.apache.org/repos/asf/cloudstack-docs-admin.git"}