{"authors.": {"authors": ["Jessica Wang", "Alena Prokharchyk", "Brian Federle", "Anthony Xu", "Rohit Yadav", "Kelven Yang", "Prasanna Santhanam", "Sheng Yang", "Min Chen", "Alex Huang", "edison su", "frank", "Edison Su", "Hugo Trippaers", "Prachi Damle", "kishan", "Girish Shilamkar", "abhishek", "Chiradeep Vittal", "Murali Reddy", "Pranav Saxena", "Chip Childers", "Wido den Hollander", "Likitha Shetty", "Nitin Mehta", "Daan Hoogland", "Radhika Puthiyetath", "David Nalley", "Marcus Sorensen", "Wei Zhou", "will", "Koushik Das", "Sanjay Tripathi", "Jayapal Uradi", "Sebastien Goasquen", "NIKITA", "nit", "Sateesh Chodapuneedi", "Abhi", "Vijayendra", "Ian Southam", "Santhosh Edukulla", "Devdeep Singh", "Joe Brockmeier", "Wilder Rodrigues", "Kris McQueen", "Mike Tutkowski", "Rajesh Battala", "Harikrishna Patnala", "Jessica Tomechak", "Srikanteswararao Talluri", "Abhinandan Prateek", "Rajani Karuturi", "Bharat kumar", "Anshul Gangwar", "Ashutosh Kelkar", "mice xia", "Manuel Amador (Rudd-O)", "Laszlo Hornyak", "Naredula Janardhana Reddy", "Leo Simons", "jessica", "saksham", "Darren Shepherd", "Salvatore Orlando", "Milamber", "Pierre-Luc Dion", "Vijay Venkatachalam", "keshav", "Chirag Jog", "Ian Duffy", "Antonio Fornie", "Hiroaki Kawai", "Damoder Reddy", "Kishan Kavala", "Frank.Zhang", "Rayees Namathponnan", "Kevin Kluge", "Chandan Purushothama", "amoghvk", "Gabor Apati-Nagy", "tuna", "ynojima", "John Kinsella", "Chris Suich", "Will Stevens", "Joris van Lieshout", "Mihaela Stoica", "Sowmya Krishnan", "Fang Wang", "John Burwell", "olivier lamy", "Gavin Lee", "JohnZ", "Amogh Vasekar", "Pradeep Soundararajan", "Isaac Chiang", "Sanjeev Neelarapu", "David Grizzanti", "Deepak Garg"], "commits": [4842, 3165, 2405, 1587, 1359, 1310, 1189, 1170, 1127, 1101, 1010, 984, 864, 822, 789, 770, 658, 606, 595, 590, 540, 487, 470, 447, 442, 434, 428, 404, 394, 379, 348, 312, 301, 291, 284, 282, 277, 275, 265, 253, 246, 218, 217, 213, 213, 209, 205, 195, 192, 182, 174, 166, 161, 159, 151, 151, 139, 138, 131, 122, 113, 102, 99, 92, 80, 76, 74, 68, 67, 66, 66, 65, 63, 61, 56, 55, 54, 50, 48, 46, 45, 44, 42, 39, 37, 37, 36, 36, 34, 32, 31, 31, 30, 30, 28, 27, 26, 26, 25, 25], "id": [13, 27, 81, 17, 143, 15, 59, 64, 190, 24, 11, 34, 14, 133, 33, 18, 261, 10, 25, 58, 101, 124, 90, 99, 75, 286, 177, 2, 180, 226, 12, 116, 102, 114, 1, 40, 30, 111, 61, 107, 367, 327, 110, 141, 338, 20, 8, 104, 218, 65, 157, 83, 334, 169, 244, 259, 146, 9, 196, 69, 425, 19, 125, 170, 105, 239, 4, 159, 50, 97, 3, 343, 178, 326, 164, 72, 277, 16, 325, 311, 384, 272, 319, 5, 313, 6, 382, 383, 299, 162, 210, 172, 174, 108, 293, 109, 211, 260, 233, 158]}, "authors.last month": {"authors": ["Ian Southam", "Hugo Trippaers", "Wilder Rodrigues", "Rohit Yadav", "Leo Simons", "Girish Shilamkar", "Daan Hoogland", "Sander Botman", "Likitha Shetty", "Rajani Karuturi", "Marcus Sorensen", "Srikanteswararao Talluri", "Koushik Das", "Mike Tutkowski", "Pierre-Luc Dion", "Anthony Xu", "Erik Weber", "Kishan Kavala", "Antonio Fornie", "Jayapal Uradi", "Laszlo Hornyak", "Pierre-Yves Ritschard", "ramamurtis", "Santhosh Edukulla", "Ashutosh Kelkar", "Abhi", "Chandan Purushothama", "Damoder Reddy", "David Nalley", "NuxRo", "Abhinav Roy", "Bharat kumar", "Devdeep Singh", "Jessica Wang", "Nitin Mehta", "Rajesh Battala", "saksham", "sanjeev", "Sateesh Chodapuneedi", "Sheng Yang", "Wei Zhou", "Yichi Lu"], "commits": [240, 111, 110, 108, 50, 23, 20, 16, 15, 15, 14, 12, 11, 9, 7, 5, 5, 5, 4, 4, 4, 4, 4, 4, 3, 2, 2, 2, 2, 2, 1, 1, 1, 1, 1, 1, 1, 1, 1, 1, 1, 1], "id": [367, 133, 338, 143, 425, 261, 286, 376, 99, 334, 180, 157, 116, 8, 4, 17, 459, 164, 343, 114, 196, 392, 35496, 327, 259, 61, 325, 326, 2, 35515, 20219, 169, 110, 13, 75, 104, 125, 454, 111, 64, 226, 203]}, "authors.last year": {"authors": ["Rohit Yadav", "Girish Shilamkar", "Daan Hoogland", "Jessica Wang", "Hugo Trippaers", "Min Chen", "Ian Southam", "Wilder Rodrigues", "Anthony Xu", "Edison Su", "Brian Federle", "Rajani Karuturi", "Murali Reddy", "Mike Tutkowski", "Santhosh Edukulla", "Alena Prokharchyk", "Jayapal Uradi", "Nitin Mehta", "Koushik Das", "Leo Simons", "Sebastien Goasquen", "Sanjay Tripathi", "Anshul Gangwar", "Sheng Yang", "Likitha Shetty", "Srikanteswararao Talluri", "Kelven Yang", "Ashutosh Kelkar", "Wido den Hollander", "Pierre-Luc Dion", "Marcus Sorensen", "Wei Zhou", "Prachi Damle", "Harikrishna Patnala", "Antonio Fornie", "Kishan Kavala", "Rajesh Battala", "Damoder Reddy", "saksham", "Chandan Purushothama", "amoghvk", "Gabor Apati-Nagy", "Laszlo Hornyak", "Bharat kumar", "Ian Duffy", "Mihaela Stoica", "Joris van Lieshout", "Sateesh Chodapuneedi", "Will Stevens", "ynojima", "Devdeep Singh", "frank", "Frank.Zhang", "Remi Bergsma", "sanjeev", "Erik Weber", "Abhi", "Prachi Damle", "Amogh Vasekar", "kishan", "Milamber", "Sailaja Mada", "Sander Botman", "Pierre-Yves Ritschard", "Rayees Namathponnan", "John Dilley", "Sangeetha Hariharan", "vinayvarmav", "Chris Suich", "Daniel Vega", "Loic Lambiel", "vetrivelc", "Alex Brett", "David Nalley", "Doug Clark", "Ilia Shakitko", "John Kinsella", "Olivier Lemasle", "seif", "David Bierce", "Sachchidanand Vaidya", "tuna", "Vincent Bernat", "Hiroki Ohashi", "punith-cloudbyte", "Radhika Puthiyetath", "Alex Huang", "Alex Hitchins", "Girish Chaudhari", "Saurav Lahiri", "Syed", "Yichi Lu", "Funs", "Keiichi Yusa", "Konstantina Chremmou", "Logan B", "Prashant Kumar Mishra", "ramamurtis", "Ren\u00e9 Moser", "Sam Schmit"], "commits": [630, 384, 286, 278, 268, 264, 241, 202, 156, 156, 155, 141, 139, 138, 137, 119, 118, 116, 115, 113, 101, 100, 97, 97, 93, 89, 87, 80, 79, 74, 71, 64, 63, 60, 56, 56, 56, 53, 47, 46, 45, 45, 40, 37, 36, 36, 35, 34, 33, 33, 30, 29, 25, 21, 21, 20, 19, 19, 18, 17, 17, 16, 16, 14, 14, 13, 13, 12, 11, 11, 11, 11, 10, 10, 10, 10, 10, 10, 9, 8, 8, 8, 8, 7, 7, 7, 6, 5, 5, 5, 5, 5, 4, 4, 4, 4, 4, 4, 4, 4], "id": [143, 261, 286, 13, 133, 190, 367, 338, 17, 14, 81, 334, 58, 8, 327, 27, 114, 75, 116, 425, 1, 102, 244, 64, 99, 157, 15, 259, 90, 4, 180, 226, 33, 218, 343, 164, 104, 326, 125, 325, 311, 384, 196, 169, 3, 383, 382, 111, 6, 319, 110, 34, 72, 35390, 454, 459, 61, 161, 293, 18, 239, 301, 376, 392, 277, 431, 70, 413, 313, 13283, 434, 375, 426, 2, 416, 7030, 5, 386, 432, 404, 365, 272, 12024, 415, 390, 177, 24, 328, 420, 412, 340, 203, 250, 35351, 380, 429, 32949, 35496, 35448, 393]}}