{"diff_netsenders_30": -1, "diff_netsenders_365": 0, "diff_netsenders_7": -1, "diff_netsent_30": 8, "diff_netsent_365": 2116, "diff_netsent_7": 15, "first_date": "2012-04-23", "last_date": "2015-07-13", "percentage_senders_30": 14, "percentage_senders_365": 0, "percentage_senders_7": 19, "percentage_sent_30": 3, "percentage_sent_365": 112, "percentage_sent_7": 39, "repositories": 6, "senders": 13, "senders_30": 6, "senders_365": 12, "senders_7": 4, "senders_init": 13, "senders_response": 13, "sent": 9677, "sent_30": 215, "sent_365": 4000, "sent_7": 53, "sent_response": 6491, "threads": 3186}