{"diff_netsenders_30": 0, "diff_netsenders_365": -1, "diff_netsenders_7": 0, "diff_netsent_30": 77, "diff_netsent_365": -2582, "diff_netsent_7": -5, "first_date": "2012-04-23", "last_date": "2016-05-27", "percentage_senders_30": 0, "percentage_senders_365": 7, "percentage_senders_7": 0, "percentage_sent_30": 62, "percentage_sent_365": 64, "percentage_sent_7": 12, "repositories": 6, "senders": 17, "senders_30": 11, "senders_365": 13, "senders_7": 6, "senders_init": 17, "senders_response": 17, "sent": 11424, "sent_30": 201, "sent_365": 1424, "sent_7": 36, "sent_response": 7934, "threads": 3490}