{"actions": 82858, "added_lines": 3120053.0, "added_lines_30": 14865.0, "added_lines_365": 278587.0, "added_lines_7": 5700.0, "authors": 36, "authors_30": 10, "authors_365": 21, "authors_7": 6, "avg_commits_author": 390.94, "avg_commits_month": 238.54, "avg_files_author": 1138.36, "avg_files_month": 694.59, "branches": 155, "commits": 14074, "commits_30": 103, "commits_365": 2385, "commits_7": 28, "committers": 34, "diff_netadded_lines_30": 8580.0, "diff_netadded_lines_365": -389923.0, "diff_netadded_lines_7": 5004.0, "diff_netauthors_30": -2, "diff_netauthors_365": -9, "diff_netauthors_7": 3, "diff_netcommits_30": 4, "diff_netcommits_365": 10, "diff_netcommits_7": 17, "diff_netfiles_30": -259, "diff_netfiles_365": -851, "diff_netfiles_7": 35, "diff_netnewauthors_30": 0, "diff_netnewauthors_365": -6, "diff_netnewauthors_7": 0, "diff_netremoved_lines_30": 4125.0, "diff_netremoved_lines_365": 1640788.0, "diff_netremoved_lines_7": 3533.0, "files": 40981, "files_30": 254, "files_365": 9053, "files_7": 91, "first_date": "2010-08-12", "last_date": "2015-08-03", "newauthors": 36, "newauthors_30": 0, "newauthors_365": 1, "newauthors_7": 0, "percentage_added_lines_30": 136, "percentage_added_lines_365": 58, "percentage_added_lines_7": 718, "percentage_authors_30": 16, "percentage_authors_365": 30, "percentage_authors_7": 100, "percentage_commits_30": 4, "percentage_commits_365": 0, "percentage_commits_7": 154, "percentage_files_30": 50, "percentage_files_365": 8, "percentage_files_7": 62, "percentage_newauthors_30": 0, "percentage_newauthors_365": 85, "percentage_newauthors_7": 0, "percentage_removed_lines_30": 132, "percentage_removed_lines_365": 283, "percentage_removed_lines_7": 1666, "removed_lines": 4689601.0, "removed_lines_30": 7241.0, "removed_lines_365": 2218853.0, "removed_lines_7": 3745.0, "repositories": 4}