{"diff_netsenders_30": 2, "diff_netsenders_365": -59, "diff_netsenders_7": 5, "diff_netsent_30": 138, "diff_netsent_365": -10281, "diff_netsent_7": 89, "first_date": "2012-04-19", "last_date": "2016-05-18", "percentage_senders_30": 6, "percentage_senders_365": 39, "percentage_senders_7": 27, "percentage_sent_30": 37, "percentage_sent_365": 64, "percentage_sent_7": 98, "repositories": 6, "senders": 276, "senders_30": 35, "senders_365": 89, "senders_7": 23, "senders_init": 269, "senders_response": 248, "sent": 64921, "sent_30": 503, "sent_365": 5537, "sent_7": 179, "sent_response": 46867, "threads": 18054}