{"actions": 126826, "added_lines": 9679725.0, "added_lines_30": 11085.0, "added_lines_365": 325419.0, "added_lines_7": 2753.0, "authors": 124, "authors_30": 16, "authors_365": 67, "authors_7": 5, "avg_commits_author": 177.02, "avg_commits_month": 378.45, "avg_files_author": 455.55, "avg_files_month": 973.93, "branches": 182, "commits": 21950, "commits_30": 167, "commits_365": 3363, "commits_7": 34, "committers": 63, "diff_netadded_lines_30": -35885.0, "diff_netadded_lines_365": -1147707.0, "diff_netadded_lines_7": 751.0, "diff_netauthors_30": 0, "diff_netauthors_365": -9, "diff_netauthors_7": -4, "diff_netcommits_30": -7, "diff_netcommits_365": -1672, "diff_netcommits_7": -12, "diff_netfiles_30": -433, "diff_netfiles_365": -7978, "diff_netfiles_7": -13, "diff_netnewauthors_30": 0, "diff_netnewauthors_365": -15, "diff_netnewauthors_7": 0, "diff_netremoved_lines_30": -13821.0, "diff_netremoved_lines_365": 1347289.0, "diff_netremoved_lines_7": 883.0, "files": 56488, "files_30": 670, "files_365": 10137, "files_7": 148, "first_date": "2010-08-11", "last_date": "2015-06-29", "newauthors": 124, "newauthors_30": 0, "newauthors_365": 18, "newauthors_7": 0, "percentage_added_lines_30": 76, "percentage_added_lines_365": 77, "percentage_added_lines_7": 37, "percentage_authors_30": 0, "percentage_authors_365": 11, "percentage_authors_7": 44, "percentage_commits_30": 4, "percentage_commits_365": 33, "percentage_commits_7": 26, "percentage_files_30": 39, "percentage_files_365": 44, "percentage_files_7": 8, "percentage_newauthors_30": 0, "percentage_newauthors_365": 45, "percentage_newauthors_7": 0, "percentage_removed_lines_30": 65, "percentage_removed_lines_365": 149, "percentage_removed_lines_7": 54, "removed_lines": 6469936.0, "removed_lines_30": 7193.0, "removed_lines_365": 2248579.0, "removed_lines_7": 2501.0, "repositories": 4}