{"actions": 137085, "added_lines": 10111696.0, "added_lines_30": 2112.0, "added_lines_365": 333601.0, "added_lines_7": 129.0, "authors": 136, "authors_30": 12, "authors_365": 68, "authors_7": 4, "avg_commits_author": 178.7, "avg_commits_month": 391.98, "avg_files_author": 434.89, "avg_files_month": 953.95, "branches": 199, "commits": 24303, "commits_30": 49, "commits_365": 3056, "commits_7": 9, "committers": 76, "diff_netadded_lines_30": -11259.0, "diff_netadded_lines_365": -731962.0, "diff_netadded_lines_7": -320.0, "diff_netauthors_30": -5, "diff_netauthors_365": -12, "diff_netauthors_7": 1, "diff_netcommits_30": -87, "diff_netcommits_365": -2185, "diff_netcommits_7": 2, "diff_netfiles_30": 598, "diff_netfiles_365": -1665, "diff_netfiles_7": -4, "diff_netnewauthors_30": -3, "diff_netnewauthors_365": -16, "diff_netnewauthors_7": 0, "diff_netremoved_lines_30": 84841.0, "diff_netremoved_lines_365": 1642744.0, "diff_netremoved_lines_7": -561.0, "files": 59145, "files_30": 1370, "files_365": 11125, "files_7": 6, "first_date": "2010-08-11", "last_date": "2015-10-17", "newauthors": 136, "newauthors_30": 0, "newauthors_365": 18, "newauthors_7": 0, "percentage_added_lines_30": 84, "percentage_added_lines_365": 68, "percentage_added_lines_7": 71, "percentage_authors_30": 29, "percentage_authors_365": 15, "percentage_authors_7": 33, "percentage_commits_30": 63, "percentage_commits_365": 41, "percentage_commits_7": 28, "percentage_files_30": 77, "percentage_files_365": 13, "percentage_files_7": 40, "percentage_newauthors_30": 100, "percentage_newauthors_365": 47, "percentage_newauthors_7": 0, "percentage_removed_lines_30": 882, "percentage_removed_lines_365": 230, "percentage_removed_lines_7": 85, "removed_lines": 6900987.0, "removed_lines_30": 94456.0, "removed_lines_365": 2354872.0, "removed_lines_7": 95.0, "repositories": 4}