{"diff_netsenders_30": 0, "diff_netsenders_365": -13, "diff_netsenders_7": 2, "diff_netsent_30": 7, "diff_netsent_365": -510, "diff_netsent_7": 12, "first_date": "2011-01-09", "last_date": "2014-11-12", "percentage_senders_30": 0, "percentage_senders_365": 44, "percentage_senders_7": 0, "percentage_sent_30": 24, "percentage_sent_365": 45, "percentage_sent_7": 0, "repositories": 5, "senders": 42, "senders_30": 5, "senders_365": 16, "senders_7": 2, "senders_init": 36, "senders_response": 34, "sent": 1974, "sent_30": 36, "sent_365": 612, "sent_7": 12, "sent_response": 1234, "threads": 740}